mpd_album_art.py
setup.py
MPD_Album_Art.egg-info/PKG-INFO
MPD_Album_Art.egg-info/SOURCES.txt
MPD_Album_Art.egg-info/dependency_links.txt
MPD_Album_Art.egg-info/requires.txt
MPD_Album_Art.egg-info/top_level.txt