Metadata-Version: 1.0
Name: MPD-Album-Art
Version: 0.1
Summary: Module to fetch Album Art for currently playing song on Music PLayer Daemon
Home-page: http://jameh.github.io/mpd-album-art
Author: Jamie Macdonald
Author-email: jamie.alban@gmail.com
License: GPL 3.0
Keywords: MPD,Album Art,LastFM
Platform: UNKNOWN
